<DialogueCommands>
    <SpeakerName
        Text_Ko="???"
        Text_En="???"
    />
    <Text 
        Text_Ko="(임시 스토리) 오, 히어로님. 일어나셨군요!"
        Text_En="(임시 스토리) 오, 히어로님. 일어나셨군요!"
    />
    <Choice>
        <Choices>
            <Item
                Text_Ko="당신은 누구?"
                Text_En="당신은 누구?"
                CommandIndex="3"
            />
            <Item
                Text_Ko="나는 누구?"
                Text_En="나는 누구?"
                CommandIndex="3"
            />
        </Choices>
    </Choice>
    <Text
        Text_Ko="당신은 지구를 지키는 &lt;color=#579C9A&gt;'비밀 히어로'&lt;/color&gt;입니다. 그리고 저는 당신의 사이드킥이죠."
        Text_En="당신은 지구를 지키는 &lt;color=#579C9A&gt;'비밀 히어로'&lt;/color&gt;입니다. 그리고 저는 당신의 사이드킥이죠."
    />
    <Choice>
        <Choices>
            <Item
                Text_Ko="아무것도 기억나지 않는데..."
                Text_En="아무것도 기억나지 않는데..."
                CommandIndex="5"
            />
        </Choices>
    </Choice>
    <Text
        Text_Ko="아아, 불행히도... 악당들의 공격을 받아 기억을 잃고 마셨군요. 능력도 잃어버리시고..."
        Text_En="아아, 불행히도... 악당들의 공격을 받아 기억을 잃고 마셨군요. 능력도 잃어버리시고..."
    />
    <Text
        Text_Ko="걱정마세요. 이제부터 다시 시작하면 되니까요. &lt;color=#579C9A&gt;'비밀 히어로'&lt;/color&gt; 일을!"
        Text_En="걱정마세요. 이제부터 다시 시작하면 되니까요. &lt;color=#579C9A&gt;'비밀 히어로'&lt;/color&gt; 일을!"
    />
    <Text
        Text_Ko="지금은 당신의 능력이 약해져있지만, 계속 사람을 돕다 보면 점점 강해질 것입니다. 힘도, 민첩도, 지능도 말이죠."
        Text_En="지금은 당신의 능력이 약해져있지만, 계속 사람을 돕다 보면 점점 강해질 것입니다. 힘도, 민첩도, 지능도 말이죠."
    />
    <Text
        Text_Ko="아, 저기 사람이 있네요! 도와주러 가볼까요? 몸풀기엔 딱이겠군요."
        Text_En="아, 저기 사람이 있네요! 도와주러 가볼까요? 몸풀기엔 딱이겠군요."
    />
</DialogueCommands>